pygmalion/__init__.py
pygmalion/_info.py
pygmalion/_model.py
pygmalion/datasets/__init__.py
pygmalion/datasets/_airline_tweets.py
pygmalion/datasets/_aquarium.py
pygmalion/datasets/_boston_housing.py
pygmalion/datasets/_cityscapes.py
pygmalion/datasets/_fashion_mnist.py
pygmalion/datasets/_iris.py
pygmalion/datasets/_sentence_pairs.py
pygmalion/datasets/_titanic.py
pygmalion/datasets/_usa_economy.py
pygmalion/datasets/generators/__init__.py
pygmalion/datasets/generators/_circles_generator.py
pygmalion/datasets/generators/_orbital_trajectory_generator.py
pygmalion/datasets/generators/_roman_numerals_generator.py
pygmalion/datasets/generators/_shapes_generator.py
pygmalion/decision_trees/__init__.py
pygmalion/decision_trees/_branch.py
pygmalion/decision_trees/_decision_tree.py
pygmalion/decision_trees/_gradient_boosting_classifier.py
pygmalion/decision_trees/_gradient_boosting_regressor.py
pygmalion/decision_trees/_monotonicity.py
pygmalion/neural_networks/__init__.py
pygmalion/neural_networks/_conversions.py
pygmalion/neural_networks/_dense_classifier.py
pygmalion/neural_networks/_dense_regressor.py
pygmalion/neural_networks/_image_classifier.py
pygmalion/neural_networks/_image_object_detector.py
pygmalion/neural_networks/_image_segmenter.py
pygmalion/neural_networks/_loss_functions.py
pygmalion/neural_networks/_neural_network.py
pygmalion/neural_networks/_probability_distribution.py
pygmalion/neural_networks/_text_classifier.py
pygmalion/neural_networks/_text_segmenter.py
pygmalion/neural_networks/_text_translator.py
pygmalion/neural_networks/_time_series_regressor.py
pygmalion/neural_networks/layers/__init__.py
pygmalion/neural_networks/layers/_activation.py
pygmalion/neural_networks/layers/_dense.py
pygmalion/neural_networks/layers/_dropout.py
pygmalion/neural_networks/layers/_layer_norm.py
pygmalion/neural_networks/layers/_normalizer.py
pygmalion/neural_networks/layers/_utilities.py
pygmalion/neural_networks/layers/convolutions/__init__.py
pygmalion-0.1.8.dist-info/LICENSE
pygmalion-0.1.8.dist-info/METADATA
pygmalion-0.1.8.dist-info/WHEEL
pygmalion-0.1.8.dist-info/top_level.txt
pygmalion-0.1.8.dist-info/RECORD
