Metadata-Version: 2.1
Name: pygmalion
Version: 0.1.8
Summary: A machine learning package
Home-page: https://github.com/BFavier/Pygmalion
Author: Benoit Favier
Author-email: benoitfamillefavier@gmail.com
License: UNKNOWN
Platform: UNKNOWN
Classifier: Programming Language :: Python :: 3
Classifier: License :: OSI Approved :: MIT License
Classifier: Operating System :: OS Independent
Classifier: Environment :: GPU :: NVIDIA CUDA
Requires-Python: >=3.8
License-File: LICENSE
Requires-Dist: pandas (>=1.0)
Requires-Dist: numpy (>=1.18)
Requires-Dist: torch (>=1.6)
Requires-Dist: requests (>=2.25)
Requires-Dist: matplotlib (>=3.2)
Requires-Dist: unidecode (>=1.3.6)
Requires-Dist: tqdm (>=4.64.0)
